perigon_news_wrapper/__init__.py
perigon_news_wrapper/perigon.py
perigon_news_wrapper-0.0.3.dist-info/LICENSE
perigon_news_wrapper-0.0.3.dist-info/METADATA
perigon_news_wrapper-0.0.3.dist-info/WHEEL
perigon_news_wrapper-0.0.3.dist-info/RECORD
