Metadata-Version: 2.1
Name: perigon-news-wrapper
Version: 0.0.3
Summary: A minimalist Python wrapper for the Perigon News API.
Home-page: https://github.com/sean-doody/perigon_news_wrapper
License: MIT
Author: Sean Doody
Author-email: sean.t.doody@gmail.com
Requires-Python: >=3.11,<4.0
Classifier: License :: OSI Approved :: MIT License
Classifier: Programming Language :: Python :: 3
Classifier: Programming Language :: Python :: 3.11
Classifier: Programming Language :: Python :: 3.12
Requires-Dist: black (>=24.4.2,<25.0.0)
Requires-Dist: pytest (>=8.3.2,<9.0.0)
Requires-Dist: requests (>=2.32.3,<3.0.0)
Requires-Dist: tenacity (>=9.0.0,<10.0.0)
Requires-Dist: tox (>=4.18.0,<5.0.0)
Requires-Dist: tqdm (>=4.66.4,<5.0.0)
Requires-Dist: urllib3 (>=2.2.2,<3.0.0)
Project-URL: Repository, https://github.com/sean-doody/perigon_news_wrapper
